usage_example.py
romy/__init__.py
romy/py.typed
romy/romy.py
romy/utils.py
romy-0.0.10.dist-info/LICENSE
romy-0.0.10.dist-info/METADATA
romy-0.0.10.dist-info/WHEEL
romy-0.0.10.dist-info/top_level.txt
romy-0.0.10.dist-info/RECORD
