Metadata-Version: 2.1
Name: romy
Version: 0.0.10
Summary: Python program and library to control Wi-Fi enabled ROMY vacuum cleaners
Author-email: Manuel Dipolt <manuel.dipolt@robart.cc>
Project-URL: Homepage, https://github.com/xeniter/romy
Project-URL: Bug Tracker, https://github.com/xeniter/romy/issues
Classifier: Programming Language :: Python :: 3
Classifier: License :: OSI Approved :: GNU Affero General Public License v3 or later (AGPLv3+)
Classifier: Operating System :: OS Independent
Classifier: Topic :: Software Development
Classifier: Topic :: Software Development :: Libraries
Classifier: Topic :: Software Development :: Libraries :: Python Modules
Classifier: Topic :: System :: Networking
Requires-Python: >=3.10
License-File: LICENSE
Requires-Dist: aiohttp>=3.8.0
Requires-Dist: async-timeout>=4.0; python_version < "3.11"
